MANIFEST.in
README.txt
setup.py
docs/HISTORY.txt
docs/INSTALL.txt
docs/LICENSE.GPL
docs/LICENSE.txt
uwosh/__init__.py
uwosh.default.egg-info/PKG-INFO
uwosh.default.egg-info/SOURCES.txt
uwosh.default.egg-info/dependency_links.txt
uwosh.default.egg-info/entry_points.txt
uwosh.default.egg-info/namespace_packages.txt
uwosh.default.egg-info/not-zip-safe
uwosh.default.egg-info/requires.txt
uwosh.default.egg-info/top_level.txt
uwosh/default/__init__.py
uwosh/default/config.py
uwosh/default/configure.zcml
uwosh/default/error_template.html
uwosh/default/importexport.py
uwosh/default/monkey.py
uwosh/default/profiles.zcml
uwosh/default/subscribers.py
uwosh/default/version.txt
uwosh/default/browser/__init__.py
uwosh/default/browser/configure.zcml
uwosh/default/browser/interfaces.py
uwosh/default/browser/only_show_body_view.pt
uwosh/default/browser/reported-errors.pt
uwosh/default/browser/views.py
uwosh/default/profiles/default/actions.xml
uwosh/default/profiles/default/browserlayer.xml
uwosh/default/profiles/default/cachesettings.xml
uwosh/default/profiles/default/contentrules.xml
uwosh/default/profiles/default/import_steps.xml
uwosh/default/profiles/default/mailhost.xml
uwosh/default/profiles/default/metadata.xml
uwosh/default/profiles/default/properties.xml
uwosh/default/profiles/default/propertiestool.xml
uwosh/default/profiles/default/types.xml
uwosh/default/profiles/default/uwosh.default.txt
uwosh/default/profiles/default/types/Document.xml
uwosh/default/tests/__init__.py
uwosh/default/tests/base.py
uwosh/default/tests/mocks.py
uwosh/default/tests/samples.py
uwosh/default/tests/test.zcml
uwosh/default/tests/test_remoteservice.py
uwosh/default/tests/test_setup.py
uwosh/default/tests/test_utils.py