Metadata-Version: 1.1
Name: uwosh.default
Version: 1.2
Summary: default settings for uwosh plone sites
Home-page: https://github.com/uwosh/uwosh.default
Author: Nathan Van Gheem
Author-email: vangheem@gmail.com
License: GPL
Platform: UNKNOWN
Classifier: Framework :: Plone
Classifier: Programming Language :: Python
Classifier: Topic :: Software Development :: Libraries :: Python Modules
